<annotation>
  <folder>VOC2007</folder>
  <filename>2020_09_10-Kratzer_20x_0.46_14_Y5_X5_op1.png</filename>
  <source>
    <database>Coco database</database>
  </source>
  <size>
    <width>256</width>
    <height>256</height>
    <depth>3</depth>
  </size>
  <segmented>0</segmented>
  <object>
    <name>d</name>
    <pose>Unspecified</pose>
    <truncated>0</truncated>
    <difficult>0</difficult>
    <bndbox>
      <xmin>0</xmin>
      <ymin>33</ymin>
      <xmax>103</xmax>
      <ymax>222</ymax>
    </bndbox>
  </object>
  <object>
    <name>d</name>
    <pose>Unspecified</pose>
    <truncated>0</truncated>
    <difficult>0</difficult>
    <bndbox>
      <xmin>1</xmin>
      <ymin>31</ymin>
      <xmax>255</xmax>
      <ymax>102</ymax>
    </bndbox>
  </object>
</annotation>
